rsack/__init__.py
rsack/bugs.py
rsack/exceptions.py
rsack/genie.py
rsack/kkbox.py
rsack/main.py
rsack/utils.py
rsack/version.py
rsack/clients/__init__.py
rsack/clients/bugs.py
rsack/clients/genie.py
rsack/clients/kkbox.py
rsack-0.7.71.dist-info/LICENSE
rsack-0.7.71.dist-info/METADATA
rsack-0.7.71.dist-info/WHEEL
rsack-0.7.71.dist-info/entry_points.txt
rsack-0.7.71.dist-info/top_level.txt
rsack-0.7.71.dist-info/RECORD
