Metadata-Version: 2.1
Name: rsack
Version: 0.7.71
Summary: A Multi-purpose downloader.
Home-page: https://github.com/Slyyxp/rsack
Author: Slyyxp
Author-email: slyyxp@protonmail.com
License: UNKNOWN
Platform: UNKNOWN
License-File: LICENSE
Requires-Dist: requests (==2.25.1)
Requires-Dist: mutagen (==1.45.1)
Requires-Dist: loguru (==0.5.3)
Requires-Dist: pycryptodomex (==3.17)
